dialog_tag/DialogTag.py
dialog_tag/__init__.py
dialog_tag/config.py
dialog_tag/get_weights.py
dialog_tag/label_mapping.py
DialogTag-1.1.3.dist-info/LICENSE
DialogTag-1.1.3.dist-info/METADATA
DialogTag-1.1.3.dist-info/WHEEL
DialogTag-1.1.3.dist-info/top_level.txt
DialogTag-1.1.3.dist-info/RECORD
