Metadata-Version: 2.1
Name: DialogTag
Version: 1.1.3
Summary: A python library to classify dialogue tag.
Home-page: https://github.com/bhavitvyamalik/DialogTag
Author: Bhavitvya Malik
Author-email: bhavitvya.malik@gmail.com
License: UNKNOWN
Keywords: Tensorflow BERT NLP deep learning Transformer Networks
Platform: UNKNOWN
Classifier: Programming Language :: Python :: 3
Classifier: License :: OSI Approved :: MIT License
Classifier: Operating System :: OS Independent
Requires-Python: >=3.7
Requires-Dist: transformers (>=3.0.0)
Requires-Dist: tqdm
Requires-Dist: tensorflow (>=2.0.0)
